Metadata-Version: 2.1
Name: odoo-addon-crm_lead_currency
Version: 17.0.1.0.1
Requires-Python: >=3.10
Requires-Dist: odoo>=17.0a,<17.1dev
Summary: On leads/opportunities, add the amount in the customer's currency.
Home-page: https://github.com/OCA/crm
License: AGPL-3
Author: Camptocamp SA,Odoo Community Association (OCA),Vauxoo
Author-email: support@odoo-community.org
Classifier: Programming Language :: Python
Classifier: Framework :: Odoo
Classifier: Framework :: Odoo :: 17.0
Classifier: License :: OSI Approved :: GNU Affero General Public License v3
